AUTHORS
CHANGES
LICENSE
MANIFEST.in
README.md
setup.py
trulia/__init__.py
trulia/location.py
trulia/stats.py
trulia.egg-info/PKG-INFO
trulia.egg-info/SOURCES.txt
trulia.egg-info/dependency_links.txt
trulia.egg-info/requires.txt
trulia.egg-info/top_level.txt