Metadata-Version: 1.0
Name: trulia
Version: 0.0.3
Summary: Python library for accessing trulia.com's REST API
Home-page: https://github.com/mattkoskela/trulia
Author: Matt Koskela
Author-email: mattkoskela@gmail.com
License: LICENSE
Platform: UNKNOWN
